convenience/__init__.py
convenience/convenience.py
convenience-0.2.dist-info/METADATA
convenience-0.2.dist-info/RECORD
convenience-0.2.dist-info/WHEEL
convenience-0.2.dist-info/top_level.txt
