Metadata-Version: 2.1
Name: convenience
Version: 0.2
Summary: Convenience tool: wrapper around regular/gzip files, Logger, text colors
Home-page: https://gitlab.com/sylvainraybaud/convenience
Author: Sylvain Raybaud
Author-email: sylvain.raybaud@crans.org
License: UNKNOWN
Platform: UNKNOWN
Classifier: Programming Language :: Python :: 3
Classifier: License :: OSI Approved :: BSD License
Classifier: Operating System :: OS Independent
